{
    "sourceFile": "skillswap-core/src/main/java/com/skillswap/skillswap_core/repository/IUsuarioRepository.java",
    "activeCommit": 0,
    "commits": [
        {
            "activePatchIndex": 4,
            "patches": [
                {
                    "date": 1717040833125,
                    "content": "Index: \n===================================================================\n--- \n+++ \n"
                },
                {
                    "date": 1717040838870,
                    "content": "Index: \n===================================================================\n--- \n+++ \n@@ -0,0 +1,3 @@\n+public interface IUsuarioRepository imple {\r\n+    \r\n+}\r\n"
                },
                {
                    "date": 1717040863255,
                    "content": "Index: \n===================================================================\n--- \n+++ \n@@ -0,0 +1,5 @@\n+package com.skillswap.skillswap_core.repository;\r\n+\r\n+public interface IUsuarioRepository {\r\n+\r\n+}\r\n"
                },
                {
                    "date": 1717040869847,
                    "content": "Index: \n===================================================================\n--- \n+++ \n@@ -1,5 +1,5 @@\n package com.skillswap.skillswap_core.repository;\r\n \r\n-public interface IUsuarioRepository imple{\r\n+public interface IUsuarioRepository impleme{\r\n \r\n }\r\n"
                },
                {
                    "date": 1717040876777,
                    "content": "Index: \n===================================================================\n--- \n+++ \n@@ -1,5 +1,7 @@\n package com.skillswap.skillswap_core.repository;\r\n \r\n-public interface IUsuarioRepository impleme{\r\n+import org.springframework.data.jpa.repository.JpaRepository;\r\n \r\n+public interface IUsuarioRepository extends JpaRepository<>{\r\n+\r\n }\r\n"
                }
            ],
            "date": 1717040833125,
            "name": "Commit-0",
            "content": "public class IUsuarioRepository {\r\n    \r\n}\r\n"
        }
    ]
}